pysshops/__init__.py
pysshops/pysshops.py
pysshops-0.2.2.dist-info/METADATA
pysshops-0.2.2.dist-info/RECORD
pysshops-0.2.2.dist-info/WHEEL
pysshops-0.2.2.dist-info/top_level.txt
